qwhale_logs_client/__init__.py
qwhale_logs_client/main.py
qwhale_logs_client-0.1.14.dist-info/LICENSE
qwhale_logs_client-0.1.14.dist-info/METADATA
qwhale_logs_client-0.1.14.dist-info/WHEEL
qwhale_logs_client-0.1.14.dist-info/top_level.txt
qwhale_logs_client-0.1.14.dist-info/RECORD
