Metadata-Version: 2.1
Name: qwhale-logs-client
Version: 0.1.14
Summary: Python client for QwhaleLogs API
Home-page: https://logs.qwhale.ml
Author: Yehoyada.s
Author-email: hvuhsg6@gmail.com
License: MIT
Keywords: API,Client,Qwhale,QWhale,client,Logs,log,logs
Platform: UNKNOWN
Classifier: Development Status :: 3 - Alpha
Classifier: Intended Audience :: Developers
Classifier: Topic :: Software Development :: Build Tools
Classifier: License :: OSI Approved :: MIT License
Classifier: Programming Language :: Python :: 3.6
Classifier: Programming Language :: Python :: 3.7
Classifier: Programming Language :: Python :: 3.8
Requires-Dist: requests
